{"type": "FeatureCollection", "features": [{"type": "Feature", "geometry": {"type": "Point", "coordinates": [139.7636101100752, 35.678700390899024, -21.8]}, "properties": {"id": "75fef7e16abb47bdb0036409c222d7cb", "category": "F017", "floor_id": "1996b4a528a146cf98915e47ed27605c", "name": null, "source": "1", "__floor": "B2", "__z_abs": -21.8}}, {"type": "Feature", "geometry": {"type": "Point", "coordinates": [139.7634366590493, 35.678873190361166, -21.8]}, "properties": {"id": "0640a49c24d647f383cd2f41a36e8f5a", "category": "F017", "floor_id": "1996b4a528a146cf98915e47ed27605c", "name": null, "source": "1", "__floor": "B2", "__z_abs": -21.8}}, {"type": "Feature", "geometry": {"type": "Point", "coordinates": [139.76343630579785, 35.67887327322395, -21.8]}, "properties": {"id": "60ecf994feb24c469d82a18360ea2a30", "category": "F012", "floor_id": "1996b4a528a146cf98915e47ed27605c", "name": null, "source": "1", "__floor": "B2", "__z_abs": -21.8}}, {"type": "Feature", "geometry": {"type": "Point", "coordinates": [139.76342245274836, 35.6787442540844, -21.8]}, "properties": {"id": "75cd71deea644afca8748241d4297d08", "category": "F013", "floor_id": "1996b4a528a146cf98915e47ed27605c", "name": null, "source": "1", "__floor": "B2", "__z_abs": -21.8}}, {"type": "Feature", "geometry": {"type": "Point", "coordinates": [139.76341803739393, 35.67873177065205, -21.8]}, "properties": {"id": "1220b1d128394c2093781149110f8d9c", "category": "F011", "floor_id": "1996b4a528a146cf98915e47ed27605c", "name": null, "source": "1", "__floor": "B2", "__z_abs": -21.8}}]}